ghb/__init__.py
ghb/__main__.py
ghb/approve.py
ghb/assignme.py
ghb/block.py
ghb/clear_comments.py
ghb/close_prs.py
ghb/comment.py
ghb/contributions.py
ghb/create.py
ghb/delete_branches.py
ghb/download_release.py
ghb/get_blocks.py
ghb/greenify.py
ghb/langs.py
ghb/ls_notifications.py
ghb/me.py
ghb/notifications.py
ghb/pr.py
ghb/protect.py
ghb/remove_review_requests.py
ghb/request_reviewers.py
ghb/unblock.py
ghb/unwatch.py
ghb/watch.py
ghb/helpers/__init__.py
ghb/helpers/credentials.py
ghb/helpers/pr.py
ghb-1.13.0.dist-info/licenses/LICENSE
ghb-1.13.0.dist-info/METADATA
ghb-1.13.0.dist-info/WHEEL
ghb-1.13.0.dist-info/entry_points.txt
ghb-1.13.0.dist-info/top_level.txt
ghb-1.13.0.dist-info/RECORD
