Metadata-Version: 2.4
Name: ghb
Version: 1.13.0
Summary: A collection of useful GitHub commands
Home-page: https://github.com/keith/ghb
Author: Keith Smiley
Author-email: keithbsmiley@gmail.com
License: MIT
Requires-Python: >=3.11
License-File: LICENSE
Requires-Dist: requests==2.32.4
Dynamic: author
Dynamic: author-email
Dynamic: description
Dynamic: home-page
Dynamic: license
Dynamic: license-file
Dynamic: requires-dist
Dynamic: requires-python
Dynamic: summary
